CHANGES.txt
LICENSE.txt
MANIFEST.in
README.txt
setup.py
js/__init__.py
js.crossroads.egg-info/PKG-INFO
js.crossroads.egg-info/SOURCES.txt
js.crossroads.egg-info/dependency_links.txt
js.crossroads.egg-info/entry_points.txt
js.crossroads.egg-info/namespace_packages.txt
js.crossroads.egg-info/not-zip-safe
js.crossroads.egg-info/requires.txt
js.crossroads.egg-info/top_level.txt
js/crossroads/__init__.py
js/crossroads/test_crossroads.js.txt
js/crossroads/resources/crossroads.js
js/crossroads/resources/crossroads.min.js