Metadata-Version: 1.0
Name: js.crossroads
Version: 0.10.0-1
Summary: Fanstatic packaging of Crossroads.js
Home-page: UNKNOWN
Author: UNKNOWN
Author-email: UNKNOWN
License: MIT
Platform: UNKNOWN
